{
  "date_iso": "2026-07-22",
  "date_human": "Wednesday, July 22, 2026",
  "summary": "Independent journalism on America",
  "countries": [
    {
      "flag": "🔎",
      "name": "Investigative & nonprofit",
      "region": "Follow-the-money reporting",
      "items": [
        {
          "outlet": "ProPublica",
          "lean": "invest",
          "title": "Trump Is Defying Congress on Foreign Aid",
          "url": "https://www.propublica.org/article/trump-defying-congress-foreign-aid-usaid-vought-rubio-constitutional-crisis"
        },
        {
          "outlet": "ProPublica",
          "lean": "invest",
          "title": "Six Senators Accuse Deputy Attorney General of “Glaring” Crypto Conflict, Cite ProPublica Investigation",
          "url": "https://www.propublica.org/article/todd-blanche-crypto-conflict-senator-letter"
        }
      ]
    },
    {
      "flag": "🇺🇸",
      "name": "Independent left (U.S.)",
      "region": "Adversarial, progressive",
      "items": [
        {
          "outlet": "The Intercept",
          "lean": "left",
          "date": "2026-07-21",
          "title": "“Cover-Up” Unravels as Pentagon Admits Nearly 100 Injured in Iran Strikes",
          "url": "https://theintercept.com/2026/07/21/iran-war-pentagon-casualties-injuries/"
        },
        {
          "outlet": "The Intercept",
          "lean": "left",
          "date": "2026-07-20",
          "title": "Hegseth’s War Department Slashed Civilian Protection Staff, Brought in AI Assessments",
          "url": "https://theintercept.com/2026/07/20/hegseth-civilian-harm-deaths-war/"
        },
        {
          "outlet": "Jacobin",
          "lean": "left",
          "title": "Unable to Accept Defeat, Donald Trump Presses On in Iran",
          "url": "https://jacobin.com/2026/07/iran-war-trump-mou-hormuz"
        },
        {
          "outlet": "Jacobin",
          "lean": "left",
          "title": "The Iran War’s Most Embarrassingly Wrong Pundits",
          "url": "https://jacobin.com/2026/07/iran-war-pundits-fox-trump"
        }
      ]
    },
    {
      "flag": "🗽",
      "name": "Independent right & heterodox",
      "region": "Libertarian, conservative, contrarian",
      "items": [
        {
          "outlet": "Reason",
          "lean": "libert",
          "date": "2026-07-14",
          "title": "Trump notifies Congress of renewed military action against Iran",
          "url": "https://reason.com/2026/07/14/meet-the-new-war/",
          "note": "Reason's argument is that the notification resets the 60 day War Powers clock and lets the campaign run without a vote."
        },
        {
          "outlet": "Reason",
          "lean": "libert",
          "date": "2026-07-20",
          "title": "Podcast: Is the war in Iran spiraling out of control?",
          "url": "https://reason.com/podcast/2026/07/20/is-the-war-in-iran-spiraling-out-of-control/"
        },
        {
          "outlet": "The Dispatch",
          "lean": "cright",
          "date": "2026-07-17",
          "title": "The Unrelenting Reality of the Iran War",
          "url": "https://thedispatch.com/article/trump-strait-hormuz-iran-regime-middle-east/"
        },
        {
          "outlet": "The Dispatch",
          "lean": "cright",
          "title": "The Iran Dilemma: Fast, Cheap, or Good",
          "url": "https://thedispatch.com/newsletter/boilingfrogs/iran-war-donald-trump-kharg-island-strait-of-hormuz/"
        },
        {
          "outlet": "UnHerd (UK)",
          "lean": "hetero",
          "title": "Trump’s shadow economy",
          "url": "https://unherd.com/2026/07/trumps-shadow-economy/"
        }
      ]
    },
    {
      "flag": "🕊️",
      "name": "Reporting in exile",
      "region": "Diaspora newsrooms covering home, and its US dealings, from abroad",
      "items": [
        {
          "outlet": "IranWire (Iran, in exile)",
          "lean": "exile",
          "date": "2026-07-22",
          "title": "US Concludes 11th Wave of Strikes Against Military Sites Across Iran",
          "url": "https://iranwire.com/en/news/155294-us-concludes-11th-wave-of-strikes-against-military-sites-across-iran/"
        },
        {
          "outlet": "IranWire (Iran, in exile)",
          "lean": "exile",
          "title": "U.S. Strikes Iran’s Southern Coast After Hormuz Attacks, Residents Say Civilian Livelihoods Destroyed",
          "url": "https://iranwire.com/en/features/154710-us-strikes-irans-southern-coast-after-hormuz-attacks-residents-say-civilian-livelihoods-destroyed/"
        },
        {
          "outlet": "Meduza (Russia, in exile)",
          "lean": "exile",
          "date": "2026-07-15",
          "title": "The US struck Iran for seven hours and restored the naval blockade. Trump threatened to attack Iranian power plants and bridges",
          "orig": "США семь часов наносили удары по Ирану и возобновили морскую блокаду. Трамп пригрозил атаковать иранские электростанции и мосты",
          "url": "https://meduza.io/news/2026/07/15/ssha-sem-chasov-nanosili-udary-po-iranu-i-vozobnovili-morskuyu-blokadu-tramp-prigrozil-atakovat-iranskie-elektrostantsii-i-mosty"
        },
        {
          "outlet": "The Kyiv Independent (Ukraine)",
          "lean": "exile",
          "title": "‘Make them yourself’: Trump gives Zelensky green light to produce Patriot missiles",
          "url": "https://kyivindependent.com/make-them-yourself-trump-gives-zelensky-green-light-to-produce-patriot-missiles/"
        }
      ]
    },
    {
      "flag": "🌍",
      "name": "International independent & analysis",
      "region": "Reader-funded, outside the US",
      "items": [
        {
          "outlet": "Middle East Eye",
          "lean": "indie",
          "title": "Why the US-Iran escalation over Hormuz will not be the last",
          "url": "https://www.middleeasteye.net/opinion/us-iran-escalation-over-hormuz-will-not-be-last"
        },
        {
          "outlet": "Middle East Eye",
          "lean": "indie",
          "title": "Iran strikes American military assets in Gulf and Jordan, after US hits Iranian cities",
          "url": "https://www.middleeasteye.net/news/iran-strikes-military-assets-gulf-and-jordan-after-us-hits-iranian-cities"
        },
        {
          "outlet": "The Conversation",
          "lean": "analysis",
          "title": "Despite Trump’s wishes, Iran is dragging the US into a long war",
          "url": "https://theconversation.com/despite-trumps-wishes-iran-is-dragging-the-us-into-a-long-war-287163"
        },
        {
          "outlet": "Coda Story",
          "lean": "indie",
          "title": "The AI-powered ‘forever wars’ start now",
          "url": "https://www.codastory.com/armed-conflict/the-ai-powered-forever-wars-start-now/"
        }
      ]
    }
  ]
}
